cvmatrix/__init__.py
cvmatrix/cvmatrix.py
cvmatrix/partitioner.py
cvmatrix-3.1.6.dist-info/METADATA
cvmatrix-3.1.6.dist-info/WHEEL
cvmatrix-3.1.6.dist-info/licenses/LICENSE
cvmatrix-3.1.6.dist-info/RECORD
