Metadata-Version: 2.4
Name: cvmatrix
Version: 3.1.6
Summary: Fast computation of possibly weighted and possibly centered/scaled training set kernel matrices in a cross-validation setting.
License: Apache-2.0
License-File: LICENSE
Author: Sm00thix
Author-email: oleemail@icloud.com
Maintainer: Sm00thix
Maintainer-email: oleemail@icloud.com
Requires-Python: >=3.11,<3.15
Classifier: License :: OSI Approved :: Apache Software License
Classifier: Programming Language :: Python :: 3
Classifier: Programming Language :: Python :: 3.11
Classifier: Programming Language :: Python :: 3.12
Classifier: Programming Language :: Python :: 3.13
Classifier: Programming Language :: Python :: 3.14
Requires-Dist: numpy (>=2.0.0,<3.0.0)
Project-URL: Homepage, https://cvmatrix.readthedocs.io/en/latest/
Project-URL: Repository, https://github.com/Sm00thix/CVMatrix
